LICENSE
MANIFEST.in
README.rst
requirements-dev.txt
requirements.txt
setup.py
nose_rapido.egg-info/PKG-INFO
nose_rapido.egg-info/SOURCES.txt
nose_rapido.egg-info/dependency_links.txt
nose_rapido.egg-info/entry_points.txt
nose_rapido.egg-info/requires.txt
nose_rapido.egg-info/top_level.txt
noserapido/__init__.py
noserapido/plugin.py