Metadata-Version: 1.1
Name: nose-rapido
Version: 0.0.2
Summary: 
